{
  "last_completed_phase": "F",
  "last_completed_task": "Phase F complete — 7 form kinds (opportunity/lead/task/follow_up/estimate/crew_confirmation/ticket), customer_autocomplete w/ inline create, validation + error banner + loading state, NewMenu 6 actions + keyboard shortcuts, NewButton wired across list pages",
  "current_phase": "G",
  "current_task": "Callscraper sync v2 — cursor-based pagination, delta ingestion, upstream → CRM mirroring of calls/summaries/opportunities",
  "blockers": [],
  "next_3_tasks": [
    "apps/worker/src/sync-callscraper-v2.ts — cursor-based sync runner",
    "Store sync_cursor per entity in a sync_state table",
    "Cron: every 2m delta sync, every 60m full reconciliation"
  ],
  "test_status": "tsc clean; vocab clean; href# zero; schemas verified via MCP",
  "build_status": "tsc_clean",
  "last_commit": "phase-F7: smoke gates - schema verified, priority int fix, estimates/opportunities POST hardened"
}
